fastnanquantile/__init__.py
fastnanquantile/fastnanquantile.py
fastnanquantile/xrcompat.py
fastnanquantile-0.0.2.dist-info/LICENSE
fastnanquantile-0.0.2.dist-info/METADATA
fastnanquantile-0.0.2.dist-info/WHEEL
fastnanquantile-0.0.2.dist-info/top_level.txt
fastnanquantile-0.0.2.dist-info/RECORD
