Metadata-Version: 2.1
Name: fastnanquantile
Version: 0.0.2
Summary: A package for fast nanquantile calculation
License: MIT License
Keywords: GIS,numpy,bottleneck,xarray
Classifier: Intended Audience :: Science/Research
Classifier: Intended Audience :: Developers
Classifier: License :: OSI Approved :: MIT License
Classifier: Programming Language :: Python :: 3.8
Classifier: Programming Language :: Python :: 3.9
Classifier: Programming Language :: Python :: 3.10
Classifier: Programming Language :: Python :: 3.11
Requires-Python: >=3.8
License-File: LICENSE
Requires-Dist: numba
Requires-Dist: numpy
Provides-Extra: xarray
Requires-Dist: xarray ; extra == 'xarray'
Provides-Extra: xarrayparallel
Requires-Dist: xarray[parallel] ; extra == 'xarrayparallel'
